cli/__init__.py
cli/__main__.py
cli/core/__init__.py
cli/core/constants.py
cli/core/core.py
cli/core/helpers.py
cli/core/log_message.py
cli/core/models.py
cli/scripts/add_bead_to_server.py
beadify-0.0.7.dist-info/METADATA
beadify-0.0.7.dist-info/WHEEL
beadify-0.0.7.dist-info/entry_points.txt
beadify-0.0.7.dist-info/top_level.txt
beadify-0.0.7.dist-info/RECORD
