Metadata-Version: 2.2
Name: beadify
Version: 0.0.7
Summary: A lightweight, efficient tool tailored for hobbyists looking to deploy multiple applications on a single Ubuntu-based VPS (Virtual Private Server)
Home-page: https://github.com/CodeLexis/beadify-cli
Author: Tomisin Abiodun
Author-email: decave.12357@gmail.com
Classifier: Programming Language :: Python :: 3
Classifier: License :: OSI Approved :: MIT License
Classifier: Operating System :: OS Independent
Requires-Python: >=3.8
Requires-Dist: click
Requires-Dist: colorama
Requires-Dist: paramiko
Requires-Dist: pydantic
Dynamic: author
Dynamic: author-email
Dynamic: classifier
Dynamic: description
Dynamic: description-content-type
Dynamic: home-page
Dynamic: requires-dist
Dynamic: requires-python
Dynamic: summary
